CHANGES.rst
COPYRIGHT.txt
HACKING.rst
LICENSE.txt
MANIFEST.in
README.rst
bootstrap.py
setup.py
doc/about.txt
doc/api.txt
doc/changes.txt
doc/conf.py
doc/index.txt
src/gocept/__init__.py
src/gocept.jasmine.egg-info/PKG-INFO
src/gocept.jasmine.egg-info/SOURCES.txt
src/gocept.jasmine.egg-info/dependency_links.txt
src/gocept.jasmine.egg-info/entry_points.txt
src/gocept.jasmine.egg-info/namespace_packages.txt
src/gocept.jasmine.egg-info/not-zip-safe
src/gocept.jasmine.egg-info/requires.txt
src/gocept.jasmine.egg-info/top_level.txt
src/gocept/jasmine/__init__.py
src/gocept/jasmine/jasmine.py
src/gocept/jasmine/resource.py
src/gocept/jasmine/resources/jasmine-html.js
src/gocept/jasmine/resources/jasmine.css
src/gocept/jasmine/resources/jasmine.js
src/gocept/jasmine/resources/mock-ajax.js
src/gocept/jasmine/resources/selftest.js
src/gocept/jasmine/resources/setup_jasmine.js
src/gocept/jasmine/tests/__init__.py
src/gocept/jasmine/tests/test_jasmine.py