Metadata-Version: 2.1
Name: gocept.jasmine
Version: 0.7
Summary: Jasmine integration for selenium.
Home-page: https://github.com/gocept/gocept.jasmine
Author: Sebastian Wehrmann
Author-email: mail@gocept.com
License: ZPL 2.1
Keywords: jasmine selenium test browser
Platform: UNKNOWN
Classifier: License :: OSI Approved :: Zope Public License
Classifier: Development Status :: 5 - Production/Stable
Classifier: Programming Language :: Python
Classifier: Programming Language :: Python :: 2
Classifier: Programming Language :: Python :: 2.7
Classifier: Programming Language :: Python :: 3
Classifier: Programming Language :: Python :: 3.7
Classifier: Programming Language :: Python :: 3.8
Provides-Extra: test
